src/__init__.py
src/cli.py
src/create_database.py
src/get_subs.py
src/id_extractor.py
src/parser.py
src/query.py
src/selenium_parser.py
youtube_search_tool_using_subtitles-0.1.0.dist-info/METADATA
youtube_search_tool_using_subtitles-0.1.0.dist-info/WHEEL
youtube_search_tool_using_subtitles-0.1.0.dist-info/entry_points.txt
youtube_search_tool_using_subtitles-0.1.0.dist-info/top_level.txt
youtube_search_tool_using_subtitles-0.1.0.dist-info/RECORD
