Metadata-Version: 2.4
Name: youtube-search-tool-using-subtitles
Version: 0.1.0
Summary: Search and query YouTube videos using AI embeddings
Author-email: Vesle Anne <anisimonova15@gmail.com>
Project-URL: Homepage, https://github.com/VesleAnne/Youtube_video_search_tool
Project-URL: Repository, https://github.com/VesleAnne/Youtube_video_search_tool
Project-URL: Issues, https://github.com/VesleAnne/Youtube_video_search_tool/issues
Classifier: Development Status :: 3 - Alpha
Classifier: Intended Audience :: Developers
Classifier: License :: OSI Approved :: MIT License
Classifier: Operating System :: OS Independent
Classifier: Programming Language :: Python :: 3
Classifier: Programming Language :: Python :: 3.8
Classifier: Programming Language :: Python :: 3.9
Classifier: Programming Language :: Python :: 3.10
Classifier: Programming Language :: Python :: 3.11
Requires-Python: >=3.8
Requires-Dist: gradio>=4.0.0
Requires-Dist: youtube-transcript-api>=0.6.0
Requires-Dist: selenium>=4.0.0
Requires-Dist: pandas>=1.5.0
Requires-Dist: python-dotenv>=1.0.0
Requires-Dist: langchain>=0.1.0
Requires-Dist: langchain-chroma>=0.1.0
Requires-Dist: langchain-openai>=0.1.0
Requires-Dist: langchain-google-genai>=1.0.0
Requires-Dist: google-generativeai>=0.3.0
Requires-Dist: chromadb>=0.4.0
Requires-Dist: pathlib
Requires-Dist: sentence-transformers>=2.2.0
Requires-Dist: ollama>=0.1.0
Requires-Dist: transformers>=4.30.0
Requires-Dist: torch>=2.0.0
Requires-Dist: accelerate>=0.20.0
Requires-Dist: langchain-community>=0.0.20
